rcmodel/__init__.py
rcmodel/optimisation/__init__.py
rcmodel/optimisation/optimise_rc.py
rcmodel/optimisation/prior_cooling_policy.py
rcmodel/optimisation/reinforce.py
rcmodel/physical/__init__.py
rcmodel/physical/building.py
rcmodel/physical/input_scaling.py
rcmodel/physical/room.py
rcmodel/rc_model.py
rcmodel/tools/__init__.py
rcmodel/tools/helper_functions.py
rcmodel/tools/plotting.py
rcmodel/tools/ray_actor.py
rcmodel/tools/rcmodel_dataset.py
rcmodel/tools/video_recorder.py
rcmodel-0.4.1.dist-info/LICENSE
rcmodel-0.4.1.dist-info/WHEEL
rcmodel-0.4.1.dist-info/METADATA
rcmodel-0.4.1.dist-info/RECORD
